knoepfe/MaterialIcons-Regular.codepoints
knoepfe/MaterialIcons-Regular.ttf
knoepfe/Roboto-Regular.ttf
knoepfe/__init__.py
knoepfe/__main__.py
knoepfe/config.py
knoepfe/deck.py
knoepfe/deckmanager.py
knoepfe/default.cfg
knoepfe/key.py
knoepfe/log.py
knoepfe/mockdeck.py
knoepfe/simpleobsws.py
knoepfe/wakelock.py
knoepfe/widgets/__init__.py
knoepfe/widgets/base.py
knoepfe/widgets/clock.py
knoepfe/widgets/mic_mute.py
knoepfe/widgets/obs/__init__.py
knoepfe/widgets/obs/base.py
knoepfe/widgets/obs/connector.py
knoepfe/widgets/obs/current_scene.py
knoepfe/widgets/obs/recording.py
knoepfe/widgets/obs/streaming.py
knoepfe/widgets/obs/switch_scene.py
knoepfe/widgets/text.py
knoepfe/widgets/timer.py
knoepfe-0.1.1.dist-info/LICENSE.md
knoepfe-0.1.1.dist-info/METADATA
knoepfe-0.1.1.dist-info/WHEEL
knoepfe-0.1.1.dist-info/entry_points.txt
knoepfe-0.1.1.dist-info/RECORD
