Metadata-Version: 2.1
Name: knoepfe
Version: 0.1.1
Summary: Connect and control Elgato Stream Decks
Home-page: https://github.com/lnqs/knoepfe
License: GPL-3.0-or-later
Author: Simon Hayessen
Author-email: simon@lnqs.io
Requires-Python: >=3.10,<4.0
Classifier: License :: OSI Approved :: GNU General Public License v3 or later (GPLv3+)
Classifier: Programming Language :: Python :: 3
Classifier: Programming Language :: Python :: 3.10
Classifier: Programming Language :: Python :: 3.11
Classifier: Programming Language :: Python :: 3.12
Requires-Dist: Pillow (>=10.4.0,<11.0.0)
Requires-Dist: aiorun (>=2024.8.1,<2025.0.0)
Requires-Dist: appdirs (>=1.4.4,<2.0.0)
Requires-Dist: docopt (>=0.6.2,<0.7.0)
Requires-Dist: pulsectl (>=24.8.0,<25.0.0)
Requires-Dist: pulsectl-asyncio (>=1.2.1,<2.0.0)
Requires-Dist: schema (>=0.7.7,<0.8.0)
Requires-Dist: streamdeck (>=0.9.5,<0.10.0)
Requires-Dist: websockets (>=13.1,<14.0)
Project-URL: Repository, https://github.com/lnqs/knoepfe
